covdefaults.py
covdefaults-2.3.0.dist-info/LICENSE
covdefaults-2.3.0.dist-info/METADATA
covdefaults-2.3.0.dist-info/WHEEL
covdefaults-2.3.0.dist-info/top_level.txt
covdefaults-2.3.0.dist-info/RECORD
